RetryFailed/__init__.py
RetryFailed/retry_failed.py
robotframework_retryfailed-0.1.0.dist-info/LICENSE
robotframework_retryfailed-0.1.0.dist-info/METADATA
robotframework_retryfailed-0.1.0.dist-info/WHEEL
robotframework_retryfailed-0.1.0.dist-info/top_level.txt
robotframework_retryfailed-0.1.0.dist-info/RECORD
