Metadata-Version: 2.1
Name: robotframework-retryfailed
Version: 0.1.0
Summary: A listener to automatically retry tests or tasks based on flags.
Home-page: https://github.com/MarketSquare/robotframework-retryfailed
Author: René Rohner(Snooz82)
Author-email: snooz@posteo.de
License: UNKNOWN
Platform: UNKNOWN
Classifier: Programming Language :: Python :: 3
Classifier: Programming Language :: Python :: 3.8
Classifier: Programming Language :: Python :: 3.9
Classifier: License :: OSI Approved :: Apache Software License
Classifier: Operating System :: OS Independent
Classifier: Topic :: Software Development :: Testing
Classifier: Topic :: Software Development :: Testing :: Acceptance
Classifier: Framework :: Robot Framework
Requires-Python: >=3.8.0
License-File: LICENSE
Requires-Dist: robotframework (>=4.1)
